cdetector/__init__.py
cdetector/cdetector.py
cdetector-0.1.5.dist-info/METADATA
cdetector-0.1.5.dist-info/WHEEL
cdetector-0.1.5.dist-info/top_level.txt
cdetector-0.1.5.dist-info/RECORD
